albopictus/ *Minibuf-1*
albopictus/__init__.py
albopictus/accessory.pyc
albopictus/gamma.c
albopictus/gamma.h
albopictus/incubator.c
albopictus/incubator.h
albopictus/incubator03.c
albopictus/incubator03.h
albopictus/modelAalbopictus03.c
albopictus/modelAalbopictus03.so
albopictus/modelAalbopictus08.c
albopictus/modelAalbopictus08.so
albopictus/modelAalbopictus08b.c
albopictus/modelAalbopictus08b.so
albopictus/modelAalbopictus08c.c
albopictus/modelAalbopictus08c.so
albopictus/modelAalbopictus13.c
albopictus/modelAalbopictus13.so
albopictus/modelAalbopictus18.c
albopictus/modelAalbopictus18.so
albopictus/modelCulex.c
albopictus/modelCulex.so
albopictus/modelStochAaegypti.c
albopictus/modelStochAaegypti.so
albopictus/modelStochAalbopictus.c
albopictus/modelStochAalbopictus.so
albopictus/modelStochCDZ.c
albopictus/modelStochCDZ.so
albopictus/modelStochCHIKV.c
albopictus/modelStochCHIKV.so
albopictus/modelStochSand.c
albopictus/modelStochSand.so
albopictus/modelStochSand13.c
albopictus/plotPos.pyc
albopictus/ran_gen.c
albopictus/ran_gen.h
albopictus/setPrior.pyc
albopictus/spop.c
albopictus/spop.h
albopictus/spop01.c
albopictus/spop01.h
albopictus/uthash.h
albopictus/accessory/__init__.py
albopictus/data/climate.json
albopictus/data/posterior.json
albopictus/data/prior03.json
albopictus/data/prior08.json
albopictus/data/prior13.json
albopictus/data/prior18.json
albopictus/data/priorAeae.json
albopictus/data/priorSand.json
albopictus/dataSurv/__init__.py
albopictus/plotPos/__init__.py
albopictus/population/__init__.py
albopictus/readModel/__init__.py
albopictus/setPrior/__init__.py
albopictus/setPrior/data/albopictus_F4_temp.txt
albopictus/setPrior/data/albopictus_d1_temp.txt
albopictus/setPrior/data/albopictus_d2_temp.txt
albopictus/setPrior/data/albopictus_d3_temp.txt
albopictus/setPrior/data/albopictus_d4_temp.txt
albopictus/setPrior/data/albopictus_gtc_temp.txt
albopictus/setPrior/data/albopictus_n23_dev.txt
albopictus/setPrior/data/albopictus_n23_surv.txt
albopictus-2.0.0.dist-info/licenses/LICENSE.txt
albopictus-2.0.0.dist-info/METADATA
albopictus-2.0.0.dist-info/WHEEL
albopictus-2.0.0.dist-info/top_level.txt
albopictus-2.0.0.dist-info/RECORD
