Metadata-Version: 2.4
Name: albopictus
Version: 2.0.0
Summary: Large-scale environment-driven population dynamics and disease spread models for vector-borne diseases
Home-page: https://github.com/kerguler/albopictus
Download-URL: https://github.com/kerguler/albopictus/tarball/attr: albopictus.__version__
Author: Kamil Erguler
Author-email: k.erguler@cyi.ac.cy
License: GPLv3
Keywords: stage, age, structured, gridded, global, diapause, breeding, egg, larva, pupa,,adult, mosquito, temperature, precipitation, density, photoperiod, survival,,development, fecundity, Bayesian, difference, daily, albopictus, sandfly, chikv,,chikungunya, phlebotomus, papatasi
Classifier: Intended Audience :: Science/Research
Classifier: Topic :: Scientific/Engineering
Classifier: Topic :: Scientific/Engineering :: Atmospheric Science
Classifier: Topic :: Scientific/Engineering :: Bio-Informatics
Classifier: Topic :: Scientific/Engineering :: Medical Science Apps.
License-File: LICENSE.txt
Requires-Dist: numpy
Requires-Dist: scipy
Dynamic: download-url
Dynamic: license-file
